add/__init__.py
add/add_by_three.py
divide/__init__.py
divide/divide_by_three.py
multiply/__init__.py
multiply/multiply_by_three.py
basic_fengfengzai-0.0.2.dist-info/LICENSE.txt
basic_fengfengzai-0.0.2.dist-info/METADATA
basic_fengfengzai-0.0.2.dist-info/WHEEL
basic_fengfengzai-0.0.2.dist-info/top_level.txt
basic_fengfengzai-0.0.2.dist-info/RECORD
