Metadata-Version: 2.1
Name: basic_fengfengzai
Version: 0.0.2
Summary: short package description
Home-page: http://example.com
Author: dufeng1010
Author-email: dufeng@example.com
Project-URL: Bug Tracker, http://example.com
Classifier: Programming Language :: Python :: 3
Requires-Python: >=3.6
License-File: LICENSE.txt
